pca3dvis/clusters.py
pca3dvis/matching.py
pca3dvis/pcs.py
pca3dvis/renderer.py
pca3dvis/scenes.py
pca3dvis/snapshot.py
pca3dvis/state.py
pca3dvis/trajectory.py
pca3dvis/worker.py
pca3dvis-0.0.3.dist-info/LICENSE.txt
pca3dvis-0.0.3.dist-info/METADATA
pca3dvis-0.0.3.dist-info/WHEEL
pca3dvis-0.0.3.dist-info/top_level.txt
pca3dvis-0.0.3.dist-info/RECORD
