Metadata-Version: 2.1
Name: pca3dvis
Version: 0.0.3
Summary: Visualize 3d matrices or their 3d projections easily
Home-page: https://github.com/tjstretchalot/pca3dvis
Author: Timothy Moore
Author-email: mtimothy984@gmail.com
License: CC0
Keywords: pca3dvis animations video mp4 3d
Platform: UNKNOWN
Classifier: Programming Language :: Python :: 3
Classifier: Programming Language :: Python :: 3.6
Classifier: Programming Language :: Python :: 3.7
Classifier: License :: CC0 1.0 Universal (CC0 1.0) Public Domain Dedication
Classifier: Topic :: Utilities
Requires-Python: >=3.6
Requires-Dist: pympanim
Requires-Dist: pytypeutils
Requires-Dist: numpy
Requires-Dist: matplotlib
Requires-Dist: hdbscan
Requires-Dist: pytweening
